setup.py
a21e/__init__.py
a21e.egg-info/PKG-INFO
a21e.egg-info/SOURCES.txt
a21e.egg-info/dependency_links.txt
a21e.egg-info/top_level.txt