Metadata-Version: 2.1
Name: a21e
Version: 0.0.1
Summary: a21e
Home-page: UNKNOWN
Author: Anish Agrawal
Author-email: your.email@example.com
License: UNKNOWN
Platform: UNKNOWN
